README.rst
setup.py
ueditor4tornado/__init__.py
ueditor4tornado/handler.py
ueditor4tornado/model.py
ueditor4tornado.egg-info/PKG-INFO
ueditor4tornado.egg-info/SOURCES.txt
ueditor4tornado.egg-info/dependency_links.txt
ueditor4tornado.egg-info/not-zip-safe
ueditor4tornado.egg-info/top_level.txt
ueditor4tornado/statics/ueditor/ueditor.all.js
ueditor4tornado/statics/ueditor/ueditor.all.min.js
ueditor4tornado/statics/ueditor/ueditor.config.js
ueditor4tornado/statics/ueditor/ueditor.parse.js
ueditor4tornado/statics/ueditor/ueditor.parse.min.js
ueditor4tornado/statics/ueditor/dialogs/internal.js
ueditor4tornado/statics/ueditor/dialogs/anchor/anchor.html
ueditor4tornado/statics/ueditor/dialogs/attachment/attachment.css
ueditor4tornado/statics/ueditor/dialogs/attachment/attachment.html
ueditor4tornado/statics/ueditor/dialogs/attachment/attachment.js
ueditor4tornado/statics/ueditor/dialogs/attachment/fileTypeImages/icon_chm.gif
ueditor4tornado/statics/ueditor/dialogs/attachment/fileTypeImages/icon_default.png
ueditor4tornado/statics/ueditor/dialogs/attachment/fileTypeImages/icon_doc.gif
ueditor4tornado/statics/ueditor/dialogs/attachment/fileTypeImages/icon_exe.gif
ueditor4tornado/statics/ueditor/dialogs/attachment/fileTypeImages/icon_jpg.gif
ueditor4tornado/statics/ueditor/dialogs/attachment/fileTypeImages/icon_mp3.gif
ueditor4tornado/statics/ueditor/dialogs/attachment/fileTypeImages/icon_mv.gif
ueditor4tornado/statics/ueditor/dialogs/attachment/fileTypeImages/icon_pdf.gif
ueditor4tornado/statics/ueditor/dialogs/attachment/fileTypeImages/icon_ppt.gif
ueditor4tornado/statics/ueditor/dialogs/attachment/fileTypeImages/icon_psd.gif
ueditor4tornado/statics/ueditor/dialogs/attachment/fileTypeImages/icon_rar.gif
ueditor4tornado/statics/ueditor/dialogs/attachment/fileTypeImages/icon_txt.gif
ueditor4tornado/statics/ueditor/dialogs/attachment/fileTypeImages/icon_xls.gif
ueditor4tornado/statics/ueditor/dialogs/attachment/images/alignicon.gif
ueditor4tornado/statics/ueditor/dialogs/attachment/images/alignicon.png
ueditor4tornado/statics/ueditor/dialogs/attachment/images/bg.png
ueditor4tornado/statics/ueditor/dialogs/attachment/images/file-icons.gif
