Metadata-Version: 1.1
Name: ueditor4tornado
Version: 0.1.1
Summary: light intergate Baidu Ueditor & Tornado
Home-page: github.com/jcteng
Author: jcteng
Author-email: jianchao.teng@outlook.com
License: BSD
Platform: UNKNOWN
Classifier: Development Status :: 3 - Alpha
Classifier: Environment :: Web Environment
Classifier: Intended Audience :: Developers
Classifier: License :: OSI Approved :: BSD License
Classifier: Operating System :: OS Independent
Classifier: Programming Language :: Python
